tests/__init__.py
uav4res_visualizer/Game.py
uav4res_visualizer/InfoState.py
uav4res_visualizer/MapBuildingState.py
uav4res_visualizer/MenuState.py
uav4res_visualizer/PathPlanningState.py
uav4res_visualizer/PathPlanningSubProcess.py
uav4res_visualizer/PlayState.py
uav4res_visualizer/__init__.py
uav4res_visualizer/__main__.py
uav4res_visualizer/config.py
uav4res_visualizer/helper.py
uav4res_visualizer/templates.py
uav4res_visualizer/assets/template.txt
uav4res_visualizer/assets/images/arrow.png
uav4res_visualizer/assets/images/boat.png
uav4res_visualizer/assets/images/map1.jpeg
uav4res_visualizer/assets/images/uet_logo.png
uav4res_visualizer/engine/Button.py
uav4res_visualizer/engine/GameState.py
uav4res_visualizer/engine/GameStateManager.py
uav4res_visualizer/engine/InputManager.py
uav4res_visualizer/engine/Singleton.py
uav4res_visualizer/engine/SoundManager.py
uav4res_visualizer/engine/TextManager.py
uav4res_visualizer/engine/TextureManager.py
uav4res_visualizer/engine/Window.py
uav4res_visualizer-0.2.1.dist-info/METADATA
uav4res_visualizer-0.2.1.dist-info/WHEEL
uav4res_visualizer-0.2.1.dist-info/entry_points.txt
uav4res_visualizer-0.2.1.dist-info/top_level.txt
uav4res_visualizer-0.2.1.dist-info/RECORD
